cdklabs/aws_lambda_rust/__init__.py
cdklabs/aws_lambda_rust/py.typed
cdklabs/aws_lambda_rust/_jsii/__init__.py
cdklabs/aws_lambda_rust/_jsii/aws-lambda-rust@0.0.10.jsii.tgz
cdklabs_aws_lambda_rust-0.0.10.dist-info/LICENSE
cdklabs_aws_lambda_rust-0.0.10.dist-info/METADATA
cdklabs_aws_lambda_rust-0.0.10.dist-info/WHEEL
cdklabs_aws_lambda_rust-0.0.10.dist-info/top_level.txt
cdklabs_aws_lambda_rust-0.0.10.dist-info/RECORD
